vlm_security_dll/__init__.py
vlm_security_dll/exceptions.py
vlm_security_dll/vlm_activator.py
vlm_security_dll-1.0.8.dist-info/METADATA
vlm_security_dll-1.0.8.dist-info/WHEEL
vlm_security_dll-1.0.8.dist-info/top_level.txt
vlm_security_dll-1.0.8.dist-info/RECORD
