Metadata-Version: 2.1
Name: vlm-security-dll
Version: 1.0.8
Summary: VLM-Security Python SDK
Home-page: https://github.com/VLM-Security/vlm_security_dll
Author: VLM-Security
Author-email: service@vlm-security.com
License: UNKNOWN
Platform: UNKNOWN
Classifier: Programming Language :: Python :: 3
Classifier: License :: OSI Approved :: MIT License
Requires-Python: >=3.6
